setup.py
jgconfig/DateTime.py
jgconfig/__init__.py
jgconfig/config.py
jgconfig/dingdingmsg.py
jgconfig/filetools.py
jgconfig/httptools.py
jgconfig/logtools.py
jgconfig/mysqltools.py
jgconfig/redispooltools.py
jgconfig/redistools.py
jgconfig/stringtools.py
jgconfig/times.py
jgconfig.egg-info/PKG-INFO
jgconfig.egg-info/SOURCES.txt
jgconfig.egg-info/dependency_links.txt
jgconfig.egg-info/requires.txt
jgconfig.egg-info/top_level.txt
test/__init__.py
test/test_log.py