Metadata-Version: 1.0
Name: jgconfig
Version: 1.2.11
Summary: jgconfig
Home-page: UNKNOWN
Author: jiegemena
Author-email: jiegemena@outlook.com
License: UNKNOWN
Platform: UNKNOWN
